fast_captchax/__init__.py
fast_captchax/captchax.py
fast_captchax/generator.py
fast_captchax/memory.py
fast_captchax/redis.py
fast_captchax/store.py
fast_captchax-0.1.0.dist-info/METADATA
fast_captchax-0.1.0.dist-info/WHEEL
fast_captchax-0.1.0.dist-info/RECORD
