Metadata-Version: 2.1
Name: fast-captchax
Version: 0.1.0
Summary: 
Author: Chongchen Chen
Author-email: chenkovsky@qq.com
Requires-Python: >=3.10
Classifier: Programming Language :: Python :: 3
Classifier: Programming Language :: Python :: 3.10
Classifier: Programming Language :: Python :: 3.11
Classifier: Programming Language :: Python :: 3.12
Requires-Dist: captchax (>=0.1.0,<0.2.0)
Requires-Dist: fastapi (>=0.110.0)
Requires-Dist: python-multipart (>=0.0.9)
Requires-Dist: redis (>=5.0.0)
